CHANGES.rst
LICENSE
MANIFEST.in
README.rst
example.py
setup.py
browsercookiejar/__init__.py
browsercookiejar/chrome.py
browsercookiejar/firefox.py
browsercookiejar/msie.py
browsercookiejar.egg-info/PKG-INFO
browsercookiejar.egg-info/SOURCES.txt
browsercookiejar.egg-info/dependency_links.txt
browsercookiejar.egg-info/top_level.txt