Metadata-Version: 1.1
Name: browsercookiejar
Version: 0.1
Summary: CookieJar for browsers
Home-page: https://github.com/regen100/browsercookiejar
Author: Regen
Author-email: git@exadge.com
License: MIT
Platform: Linux
Platform: Windows
Classifier: Development Status :: 3 - Alpha
Classifier: Intended Audience :: Developers
Classifier: Intended Audience :: End Users/Desktop
Classifier: License :: OSI Approved :: MIT License
Classifier: Operating System :: Microsoft :: Windows
Classifier: Operating System :: POSIX :: Linux
Classifier: Topic :: Internet :: WWW/HTTP :: Browsers
